cargoshipper_mcp/__init__.py
cargoshipper_mcp/server.py
cargoshipper_mcp/config/__init__.py
cargoshipper_mcp/config/settings.py
cargoshipper_mcp/resources/__init__.py
cargoshipper_mcp/resources/cloudflare.py
cargoshipper_mcp/resources/digitalocean.py
cargoshipper_mcp/resources/docker.py
cargoshipper_mcp/tools/__init__.py
cargoshipper_mcp/tools/cloudflare.py
cargoshipper_mcp/tools/digitalocean.py
cargoshipper_mcp/tools/docker.py
cargoshipper_mcp/utils/__init__.py
cargoshipper_mcp/utils/auth.py
cargoshipper_mcp/utils/docker_auth.py
cargoshipper_mcp/utils/errors.py
cargoshipper_mcp/utils/formatters.py
cargoshipper_mcp/utils/token_inspector.py
cargoshipper_mcp/utils/validation.py
cargoshipper_mcp-1.0.3.dist-info/licenses/LICENSE
cargoshipper_mcp-1.0.3.dist-info/METADATA
cargoshipper_mcp-1.0.3.dist-info/WHEEL
cargoshipper_mcp-1.0.3.dist-info/entry_points.txt
cargoshipper_mcp-1.0.3.dist-info/top_level.txt
cargoshipper_mcp-1.0.3.dist-info/RECORD
